{"project": {"id": 1, "project_name": "jpacman-framework"}, "method": {"id": 58, "project_id": 1, "method_name": "moveTowardsDirection", "method_decl": "Action moveTowardsDirection(Game, Player, Direction)", "class_name": "Launcher", "package_name": "nl.tudelft.jpacman", "file_path": "/src/main/java/nl/tudelft/jpacman/Launcher.java"}, "coverage": {"commits": [{"id": 1, "project_id": 1, "sha": "43aac19db93e73646297dde14dbc2c3d7f167e9e", "author": "Arie van Deursen", "datetime": "2017-04-11 20:34:17+02:00"}], "tests": [{"id": 1, "project_id": 1, "package_name": "nl.tudelft.jpacman.cucumber", "class_name": "CucumberTest", "method_name": "Given the user has launched the JPacman GUI"}, {"id": 2, "project_id": 1, "package_name": "nl.tudelft.jpacman", "class_name": "LauncherSmokeTest", "method_name": "smokeTest"}], "edges": [{"test_id": 1, "commit_id": 1, "test_result": true}, {"test_id": 2, "commit_id": 1, "test_result": true}]}}